kpcr/__init__.py
kpcr/main.py
poorna_basic-1.0.0.dist-info/METADATA
poorna_basic-1.0.0.dist-info/WHEEL
poorna_basic-1.0.0.dist-info/top_level.txt
poorna_basic-1.0.0.dist-info/RECORD
